vcx_py/__init__.py
vcx_py/client.py
vcx_py/constants.py
vcx_py/schema.py
vcx_py/utils.py
vcx_py-1.2.0.dist-info/LICENSE
vcx_py-1.2.0.dist-info/METADATA
vcx_py-1.2.0.dist-info/WHEEL
vcx_py-1.2.0.dist-info/top_level.txt
vcx_py-1.2.0.dist-info/RECORD
