Metadata-Version: 2.1
Name: vcx_py
Version: 1.2.0
Summary: A simple python client for the VirgoCX API
Home-page: https://www.github.com/aarjaneiro/vcx_py
Author: Aaron Janeiro Stone
Author-email: aaron@thequant.ca
License: MIT
License-File: LICENSE
